[
    {
        "id": 0,
        "text": "Example knowledge 0. 知识实例 0"
    },
    {
        "id": 1,
        "text": "Example knowledge 1. 知识实例 1"
    },
    {
        "id": 2,
        "text": "Example knowledge 2. 知识实例 2"
    },
    {
        "id": 3,
        "text": "Example knowledge 3. 知识实例 3"
    },
    {
        "id": 4,
        "text": "Example knowledge 4. 知识实例 4"
    },
    {
        "id": 5,
        "text": "Example knowledge 5. 知识实例 5"
    },
    {
        "id": 6,
        "text": "Example knowledge 6. 知识实例 6"
    },
    {
        "id": 7,
        "text": "Example knowledge 7. 知识实例 7"
    },
    {
        "id": 8,
        "text": "Example knowledge 8. 知识实例 8"
    },
    {
        "id": 9,
        "text": "Example knowledge 9. 知识实例 9"
    },
    {
        "id": 10,
        "text": "Example knowledge 10. 知识实例 10"
    },
    {
        "id": 11,
        "text": "Example knowledge 11. 知识实例 11"
    },
    {
        "id": 12,
        "text": "Example knowledge 12. 知识实例 12"
    },
    {
        "id": 13,
        "text": "Example knowledge 13. 知识实例 13"
    },
    {
        "id": 14,
        "text": "Example knowledge 14. 知识实例 14"
    },
    {
        "id": 15,
        "text": "Example knowledge 15. 知识实例 15"
    },
    {
        "id": 16,
        "text": "Example knowledge 16. 知识实例 16"
    },
    {
        "id": 17,
        "text": "Example knowledge 17. 知识实例 17"
    },
    {
        "id": 18,
        "text": "Example knowledge 18. 知识实例 18"
    },
    {
        "id": 19,
        "text": "Example knowledge 19. 知识实例 19"
    },
    {
        "id": 20,
        "text": "Example knowledge 20. 知识实例 20"
    },
    {
        "id": 21,
        "text": "Example knowledge 21. 知识实例 21"
    },
    {
        "id": 22,
        "text": "Example knowledge 22. 知识实例 22"
    },
    {
        "id": 23,
        "text": "Example knowledge 23. 知识实例 23"
    },
    {
        "id": 24,
        "text": "Example knowledge 24. 知识实例 24"
    },
    {
        "id": 25,
        "text": "Example knowledge 25. 知识实例 25"
    },
    {
        "id": 26,
        "text": "Example knowledge 26. 知识实例 26"
    },
    {
        "id": 27,
        "text": "Example knowledge 27. 知识实例 27"
    },
    {
        "id": 28,
        "text": "Example knowledge 28. 知识实例 28"
    },
    {
        "id": 29,
        "text": "Example knowledge 29. 知识实例 29"
    },
    {
        "id": 30,
        "text": "Example knowledge 30. 知识实例 30"
    },
    {
        "id": 31,
        "text": "Example knowledge 31. 知识实例 31"
    },
    {
        "id": 32,
        "text": "Example knowledge 32. 知识实例 32"
    },
    {
        "id": 33,
        "text": "Example knowledge 33. 知识实例 33"
    },
    {
        "id": 34,
        "text": "Example knowledge 34. 知识实例 34"
    },
    {
        "id": 35,
        "text": "Example knowledge 35. 知识实例 35"
    },
    {
        "id": 36,
        "text": "Example knowledge 36. 知识实例 36"
    },
    {
        "id": 37,
        "text": "Example knowledge 37. 知识实例 37"
    },
    {
        "id": 38,
        "text": "Example knowledge 38. 知识实例 38"
    },
    {
        "id": 39,
        "text": "Example knowledge 39. 知识实例 39"
    },
    {
        "id": 40,
        "text": "Example knowledge 40. 知识实例 40"
    },
    {
        "id": 41,
        "text": "Example knowledge 41. 知识实例 41"
    },
    {
        "id": 42,
        "text": "Example knowledge 42. 知识实例 42"
    },
    {
        "id": 43,
        "text": "Example knowledge 43. 知识实例 43"
    },
    {
        "id": 44,
        "text": "Example knowledge 44. 知识实例 44"
    },
    {
        "id": 45,
        "text": "Example knowledge 45. 知识实例 45"
    },
    {
        "id": 46,
        "text": "Example knowledge 46. 知识实例 46"
    },
    {
        "id": 47,
        "text": "Example knowledge 47. 知识实例 47"
    },
    {
        "id": 48,
        "text": "Example knowledge 48. 知识实例 48"
    },
    {
        "id": 49,
        "text": "Example knowledge 49. 知识实例 49"
    },
    {
        "id": 50,
        "text": "Example knowledge 50. 知识实例 50"
    },
    {
        "id": 51,
        "text": "Example knowledge 51. 知识实例 51"
    },
    {
        "id": 52,
        "text": "Example knowledge 52. 知识实例 52"
    },
    {
        "id": 53,
        "text": "Example knowledge 53. 知识实例 53"
    },
    {
        "id": 54,
        "text": "Example knowledge 54. 知识实例 54"
    },
    {
        "id": 55,
        "text": "Example knowledge 55. 知识实例 55"
    },
    {
        "id": 56,
        "text": "Example knowledge 56. 知识实例 56"
    },
    {
        "id": 57,
        "text": "Example knowledge 57. 知识实例 57"
    },
    {
        "id": 58,
        "text": "Example knowledge 58. 知识实例 58"
    },
    {
        "id": 59,
        "text": "Example knowledge 59. 知识实例 59"
    },
    {
        "id": 60,
        "text": "Example knowledge 60. 知识实例 60"
    },
    {
        "id": 61,
        "text": "Example knowledge 61. 知识实例 61"
    },
    {
        "id": 62,
        "text": "Example knowledge 62. 知识实例 62"
    },
    {
        "id": 63,
        "text": "Example knowledge 63. 知识实例 63"
    },
    {
        "id": 64,
        "text": "Example knowledge 64. 知识实例 64"
    },
    {
        "id": 65,
        "text": "Example knowledge 65. 知识实例 65"
    },
    {
        "id": 66,
        "text": "Example knowledge 66. 知识实例 66"
    },
    {
        "id": 67,
        "text": "Example knowledge 67. 知识实例 67"
    },
    {
        "id": 68,
        "text": "Example knowledge 68. 知识实例 68"
    },
    {
        "id": 69,
        "text": "Example knowledge 69. 知识实例 69"
    },
    {
        "id": 70,
        "text": "Example knowledge 70. 知识实例 70"
    },
    {
        "id": 71,
        "text": "Example knowledge 71. 知识实例 71"
    },
    {
        "id": 72,
        "text": "Example knowledge 72. 知识实例 72"
    },
    {
        "id": 73,
        "text": "Example knowledge 73. 知识实例 73"
    },
    {
        "id": 74,
        "text": "Example knowledge 74. 知识实例 74"
    },
    {
        "id": 75,
        "text": "Example knowledge 75. 知识实例 75"
    },
    {
        "id": 76,
        "text": "Example knowledge 76. 知识实例 76"
    },
    {
        "id": 77,
        "text": "Example knowledge 77. 知识实例 77"
    },
    {
        "id": 78,
        "text": "Example knowledge 78. 知识实例 78"
    },
    {
        "id": 79,
        "text": "Example knowledge 79. 知识实例 79"
    },
    {
        "id": 80,
        "text": "Example knowledge 80. 知识实例 80"
    },
    {
        "id": 81,
        "text": "Example knowledge 81. 知识实例 81"
    },
    {
        "id": 82,
        "text": "Example knowledge 82. 知识实例 82"
    },
    {
        "id": 83,
        "text": "Example knowledge 83. 知识实例 83"
    },
    {
        "id": 84,
        "text": "Example knowledge 84. 知识实例 84"
    },
    {
        "id": 85,
        "text": "Example knowledge 85. 知识实例 85"
    },
    {
        "id": 86,
        "text": "Example knowledge 86. 知识实例 86"
    },
    {
        "id": 87,
        "text": "Example knowledge 87. 知识实例 87"
    },
    {
        "id": 88,
        "text": "Example knowledge 88. 知识实例 88"
    },
    {
        "id": 89,
        "text": "Example knowledge 89. 知识实例 89"
    },
    {
        "id": 90,
        "text": "Example knowledge 90. 知识实例 90"
    },
    {
        "id": 91,
        "text": "Example knowledge 91. 知识实例 91"
    },
    {
        "id": 92,
        "text": "Example knowledge 92. 知识实例 92"
    },
    {
        "id": 93,
        "text": "Example knowledge 93. 知识实例 93"
    },
    {
        "id": 94,
        "text": "Example knowledge 94. 知识实例 94"
    },
    {
        "id": 95,
        "text": "Example knowledge 95. 知识实例 95"
    },
    {
        "id": 96,
        "text": "Example knowledge 96. 知识实例 96"
    },
    {
        "id": 97,
        "text": "Example knowledge 97. 知识实例 97"
    },
    {
        "id": 98,
        "text": "Example knowledge 98. 知识实例 98"
    },
    {
        "id": 99,
        "text": "Example knowledge 99. 知识实例 99"
    },
    {
        "id": 100,
        "text": "Example knowledge 100. 知识实例 100"
    },
    {
        "id": 101,
        "text": "Example knowledge 101. 知识实例 101"
    },
    {
        "id": 102,
        "text": "Example knowledge 102. 知识实例 102"
    },
    {
        "id": 103,
        "text": "Example knowledge 103. 知识实例 103"
    },
    {
        "id": 104,
        "text": "Example knowledge 104. 知识实例 104"
    },
    {
        "id": 105,
        "text": "Example knowledge 105. 知识实例 105"
    },
    {
        "id": 106,
        "text": "Example knowledge 106. 知识实例 106"
    },
    {
        "id": 107,
        "text": "Example knowledge 107. 知识实例 107"
    },
    {
        "id": 108,
        "text": "Example knowledge 108. 知识实例 108"
    },
    {
        "id": 109,
        "text": "Example knowledge 109. 知识实例 109"
    },
    {
        "id": 110,
        "text": "Example knowledge 110. 知识实例 110"
    },
    {
        "id": 111,
        "text": "Example knowledge 111. 知识实例 111"
    },
    {
        "id": 112,
        "text": "Example knowledge 112. 知识实例 112"
    },
    {
        "id": 113,
        "text": "Example knowledge 113. 知识实例 113"
    },
    {
        "id": 114,
        "text": "Example knowledge 114. 知识实例 114"
    },
    {
        "id": 115,
        "text": "Example knowledge 115. 知识实例 115"
    },
    {
        "id": 116,
        "text": "Example knowledge 116. 知识实例 116"
    },
    {
        "id": 117,
        "text": "Example knowledge 117. 知识实例 117"
    },
    {
        "id": 118,
        "text": "Example knowledge 118. 知识实例 118"
    },
    {
        "id": 119,
        "text": "Example knowledge 119. 知识实例 119"
    },
    {
        "id": 120,
        "text": "Example knowledge 120. 知识实例 120"
    },
    {
        "id": 121,
        "text": "Example knowledge 121. 知识实例 121"
    },
    {
        "id": 122,
        "text": "Example knowledge 122. 知识实例 122"
    },
    {
        "id": 123,
        "text": "Example knowledge 123. 知识实例 123"
    },
    {
        "id": 124,
        "text": "Example knowledge 124. 知识实例 124"
    },
    {
        "id": 125,
        "text": "Example knowledge 125. 知识实例 125"
    },
    {
        "id": 126,
        "text": "Example knowledge 126. 知识实例 126"
    },
    {
        "id": 127,
        "text": "Example knowledge 127. 知识实例 127"
    },
    {
        "id": 128,
        "text": "Example knowledge 128. 知识实例 128"
    },
    {
        "id": 129,
        "text": "Example knowledge 129. 知识实例 129"
    },
    {
        "id": 130,
        "text": "Example knowledge 130. 知识实例 130"
    },
    {
        "id": 131,
        "text": "Example knowledge 131. 知识实例 131"
    },
    {
        "id": 132,
        "text": "Example knowledge 132. 知识实例 132"
    },
    {
        "id": 133,
        "text": "Example knowledge 133. 知识实例 133"
    },
    {
        "id": 134,
        "text": "Example knowledge 134. 知识实例 134"
    },
    {
        "id": 135,
        "text": "Example knowledge 135. 知识实例 135"
    },
    {
        "id": 136,
        "text": "Example knowledge 136. 知识实例 136"
    },
    {
        "id": 137,
        "text": "Example knowledge 137. 知识实例 137"
    },
    {
        "id": 138,
        "text": "Example knowledge 138. 知识实例 138"
    },
    {
        "id": 139,
        "text": "Example knowledge 139. 知识实例 139"
    },
    {
        "id": 140,
        "text": "Example knowledge 140. 知识实例 140"
    },
    {
        "id": 141,
        "text": "Example knowledge 141. 知识实例 141"
    },
    {
        "id": 142,
        "text": "Example knowledge 142. 知识实例 142"
    },
    {
        "id": 143,
        "text": "Example knowledge 143. 知识实例 143"
    },
    {
        "id": 144,
        "text": "Example knowledge 144. 知识实例 144"
    },
    {
        "id": 145,
        "text": "Example knowledge 145. 知识实例 145"
    },
    {
        "id": 146,
        "text": "Example knowledge 146. 知识实例 146"
    },
    {
        "id": 147,
        "text": "Example knowledge 147. 知识实例 147"
    },
    {
        "id": 148,
        "text": "Example knowledge 148. 知识实例 148"
    },
    {
        "id": 149,
        "text": "Example knowledge 149. 知识实例 149"
    },
    {
        "id": 150,
        "text": "Example knowledge 150. 知识实例 150"
    },
    {
        "id": 151,
        "text": "Example knowledge 151. 知识实例 151"
    },
    {
        "id": 152,
        "text": "Example knowledge 152. 知识实例 152"
    },
    {
        "id": 153,
        "text": "Example knowledge 153. 知识实例 153"
    },
    {
        "id": 154,
        "text": "Example knowledge 154. 知识实例 154"
    },
    {
        "id": 155,
        "text": "Example knowledge 155. 知识实例 155"
    },
    {
        "id": 156,
        "text": "Example knowledge 156. 知识实例 156"
    },
    {
        "id": 157,
        "text": "Example knowledge 157. 知识实例 157"
    },
    {
        "id": 158,
        "text": "Example knowledge 158. 知识实例 158"
    },
    {
        "id": 159,
        "text": "Example knowledge 159. 知识实例 159"
    },
    {
        "id": 160,
        "text": "Example knowledge 160. 知识实例 160"
    },
    {
        "id": 161,
        "text": "Example knowledge 161. 知识实例 161"
    },
    {
        "id": 162,
        "text": "Example knowledge 162. 知识实例 162"
    },
    {
        "id": 163,
        "text": "Example knowledge 163. 知识实例 163"
    },
    {
        "id": 164,
        "text": "Example knowledge 164. 知识实例 164"
    },
    {
        "id": 165,
        "text": "Example knowledge 165. 知识实例 165"
    },
    {
        "id": 166,
        "text": "Example knowledge 166. 知识实例 166"
    },
    {
        "id": 167,
        "text": "Example knowledge 167. 知识实例 167"
    },
    {
        "id": 168,
        "text": "Example knowledge 168. 知识实例 168"
    },
    {
        "id": 169,
        "text": "Example knowledge 169. 知识实例 169"
    },
    {
        "id": 170,
        "text": "Example knowledge 170. 知识实例 170"
    },
    {
        "id": 171,
        "text": "Example knowledge 171. 知识实例 171"
    },
    {
        "id": 172,
        "text": "Example knowledge 172. 知识实例 172"
    },
    {
        "id": 173,
        "text": "Example knowledge 173. 知识实例 173"
    },
    {
        "id": 174,
        "text": "Example knowledge 174. 知识实例 174"
    },
    {
        "id": 175,
        "text": "Example knowledge 175. 知识实例 175"
    },
    {
        "id": 176,
        "text": "Example knowledge 176. 知识实例 176"
    },
    {
        "id": 177,
        "text": "Example knowledge 177. 知识实例 177"
    },
    {
        "id": 178,
        "text": "Example knowledge 178. 知识实例 178"
    },
    {
        "id": 179,
        "text": "Example knowledge 179. 知识实例 179"
    },
    {
        "id": 180,
        "text": "Example knowledge 180. 知识实例 180"
    },
    {
        "id": 181,
        "text": "Example knowledge 181. 知识实例 181"
    },
    {
        "id": 182,
        "text": "Example knowledge 182. 知识实例 182"
    },
    {
        "id": 183,
        "text": "Example knowledge 183. 知识实例 183"
    },
    {
        "id": 184,
        "text": "Example knowledge 184. 知识实例 184"
    },
    {
        "id": 185,
        "text": "Example knowledge 185. 知识实例 185"
    },
    {
        "id": 186,
        "text": "Example knowledge 186. 知识实例 186"
    },
    {
        "id": 187,
        "text": "Example knowledge 187. 知识实例 187"
    },
    {
        "id": 188,
        "text": "Example knowledge 188. 知识实例 188"
    },
    {
        "id": 189,
        "text": "Example knowledge 189. 知识实例 189"
    },
    {
        "id": 190,
        "text": "Example knowledge 190. 知识实例 190"
    },
    {
        "id": 191,
        "text": "Example knowledge 191. 知识实例 191"
    },
    {
        "id": 192,
        "text": "Example knowledge 192. 知识实例 192"
    },
    {
        "id": 193,
        "text": "Example knowledge 193. 知识实例 193"
    },
    {
        "id": 194,
        "text": "Example knowledge 194. 知识实例 194"
    },
    {
        "id": 195,
        "text": "Example knowledge 195. 知识实例 195"
    },
    {
        "id": 196,
        "text": "Example knowledge 196. 知识实例 196"
    },
    {
        "id": 197,
        "text": "Example knowledge 197. 知识实例 197"
    },
    {
        "id": 198,
        "text": "Example knowledge 198. 知识实例 198"
    },
    {
        "id": 199,
        "text": "Example knowledge 199. 知识实例 199"
    },
    {
        "id": 200,
        "text": "Example knowledge 200. 知识实例 200"
    },
    {
        "id": 201,
        "text": "Example knowledge 201. 知识实例 201"
    },
    {
        "id": 202,
        "text": "Example knowledge 202. 知识实例 202"
    },
    {
        "id": 203,
        "text": "Example knowledge 203. 知识实例 203"
    },
    {
        "id": 204,
        "text": "Example knowledge 204. 知识实例 204"
    },
    {
        "id": 205,
        "text": "Example knowledge 205. 知识实例 205"
    },
    {
        "id": 206,
        "text": "Example knowledge 206. 知识实例 206"
    },
    {
        "id": 207,
        "text": "Example knowledge 207. 知识实例 207"
    },
    {
        "id": 208,
        "text": "Example knowledge 208. 知识实例 208"
    },
    {
        "id": 209,
        "text": "Example knowledge 209. 知识实例 209"
    },
    {
        "id": 210,
        "text": "Example knowledge 210. 知识实例 210"
    },
    {
        "id": 211,
        "text": "Example knowledge 211. 知识实例 211"
    },
    {
        "id": 212,
        "text": "Example knowledge 212. 知识实例 212"
    },
    {
        "id": 213,
        "text": "Example knowledge 213. 知识实例 213"
    },
    {
        "id": 214,
        "text": "Example knowledge 214. 知识实例 214"
    },
    {
        "id": 215,
        "text": "Example knowledge 215. 知识实例 215"
    },
    {
        "id": 216,
        "text": "Example knowledge 216. 知识实例 216"
    },
    {
        "id": 217,
        "text": "Example knowledge 217. 知识实例 217"
    },
    {
        "id": 218,
        "text": "Example knowledge 218. 知识实例 218"
    },
    {
        "id": 219,
        "text": "Example knowledge 219. 知识实例 219"
    },
    {
        "id": 220,
        "text": "Example knowledge 220. 知识实例 220"
    },
    {
        "id": 221,
        "text": "Example knowledge 221. 知识实例 221"
    },
    {
        "id": 222,
        "text": "Example knowledge 222. 知识实例 222"
    },
    {
        "id": 223,
        "text": "Example knowledge 223. 知识实例 223"
    },
    {
        "id": 224,
        "text": "Example knowledge 224. 知识实例 224"
    },
    {
        "id": 225,
        "text": "Example knowledge 225. 知识实例 225"
    },
    {
        "id": 226,
        "text": "Example knowledge 226. 知识实例 226"
    },
    {
        "id": 227,
        "text": "Example knowledge 227. 知识实例 227"
    },
    {
        "id": 228,
        "text": "Example knowledge 228. 知识实例 228"
    },
    {
        "id": 229,
        "text": "Example knowledge 229. 知识实例 229"
    },
    {
        "id": 230,
        "text": "Example knowledge 230. 知识实例 230"
    },
    {
        "id": 231,
        "text": "Example knowledge 231. 知识实例 231"
    },
    {
        "id": 232,
        "text": "Example knowledge 232. 知识实例 232"
    },
    {
        "id": 233,
        "text": "Example knowledge 233. 知识实例 233"
    },
    {
        "id": 234,
        "text": "Example knowledge 234. 知识实例 234"
    },
    {
        "id": 235,
        "text": "Example knowledge 235. 知识实例 235"
    },
    {
        "id": 236,
        "text": "Example knowledge 236. 知识实例 236"
    },
    {
        "id": 237,
        "text": "Example knowledge 237. 知识实例 237"
    },
    {
        "id": 238,
        "text": "Example knowledge 238. 知识实例 238"
    },
    {
        "id": 239,
        "text": "Example knowledge 239. 知识实例 239"
    },
    {
        "id": 240,
        "text": "Example knowledge 240. 知识实例 240"
    },
    {
        "id": 241,
        "text": "Example knowledge 241. 知识实例 241"
    },
    {
        "id": 242,
        "text": "Example knowledge 242. 知识实例 242"
    },
    {
        "id": 243,
        "text": "Example knowledge 243. 知识实例 243"
    },
    {
        "id": 244,
        "text": "Example knowledge 244. 知识实例 244"
    },
    {
        "id": 245,
        "text": "Example knowledge 245. 知识实例 245"
    },
    {
        "id": 246,
        "text": "Example knowledge 246. 知识实例 246"
    },
    {
        "id": 247,
        "text": "Example knowledge 247. 知识实例 247"
    },
    {
        "id": 248,
        "text": "Example knowledge 248. 知识实例 248"
    },
    {
        "id": 249,
        "text": "Example knowledge 249. 知识实例 249"
    },
    {
        "id": 250,
        "text": "Example knowledge 250. 知识实例 250"
    },
    {
        "id": 251,
        "text": "Example knowledge 251. 知识实例 251"
    },
    {
        "id": 252,
        "text": "Example knowledge 252. 知识实例 252"
    },
    {
        "id": 253,
        "text": "Example knowledge 253. 知识实例 253"
    },
    {
        "id": 254,
        "text": "Example knowledge 254. 知识实例 254"
    },
    {
        "id": 255,
        "text": "Example knowledge 255. 知识实例 255"
    },
    {
        "id": 256,
        "text": "Example knowledge 256. 知识实例 256"
    },
    {
        "id": 257,
        "text": "Example knowledge 257. 知识实例 257"
    },
    {
        "id": 258,
        "text": "Example knowledge 258. 知识实例 258"
    },
    {
        "id": 259,
        "text": "Example knowledge 259. 知识实例 259"
    },
    {
        "id": 260,
        "text": "Example knowledge 260. 知识实例 260"
    },
    {
        "id": 261,
        "text": "Example knowledge 261. 知识实例 261"
    },
    {
        "id": 262,
        "text": "Example knowledge 262. 知识实例 262"
    },
    {
        "id": 263,
        "text": "Example knowledge 263. 知识实例 263"
    },
    {
        "id": 264,
        "text": "Example knowledge 264. 知识实例 264"
    },
    {
        "id": 265,
        "text": "Example knowledge 265. 知识实例 265"
    },
    {
        "id": 266,
        "text": "Example knowledge 266. 知识实例 266"
    },
    {
        "id": 267,
        "text": "Example knowledge 267. 知识实例 267"
    },
    {
        "id": 268,
        "text": "Example knowledge 268. 知识实例 268"
    },
    {
        "id": 269,
        "text": "Example knowledge 269. 知识实例 269"
    },
    {
        "id": 270,
        "text": "Example knowledge 270. 知识实例 270"
    },
    {
        "id": 271,
        "text": "Example knowledge 271. 知识实例 271"
    },
    {
        "id": 272,
        "text": "Example knowledge 272. 知识实例 272"
    },
    {
        "id": 273,
        "text": "Example knowledge 273. 知识实例 273"
    },
    {
        "id": 274,
        "text": "Example knowledge 274. 知识实例 274"
    },
    {
        "id": 275,
        "text": "Example knowledge 275. 知识实例 275"
    },
    {
        "id": 276,
        "text": "Example knowledge 276. 知识实例 276"
    },
    {
        "id": 277,
        "text": "Example knowledge 277. 知识实例 277"
    },
    {
        "id": 278,
        "text": "Example knowledge 278. 知识实例 278"
    },
    {
        "id": 279,
        "text": "Example knowledge 279. 知识实例 279"
    },
    {
        "id": 280,
        "text": "Example knowledge 280. 知识实例 280"
    },
    {
        "id": 281,
        "text": "Example knowledge 281. 知识实例 281"
    },
    {
        "id": 282,
        "text": "Example knowledge 282. 知识实例 282"
    },
    {
        "id": 283,
        "text": "Example knowledge 283. 知识实例 283"
    },
    {
        "id": 284,
        "text": "Example knowledge 284. 知识实例 284"
    },
    {
        "id": 285,
        "text": "Example knowledge 285. 知识实例 285"
    },
    {
        "id": 286,
        "text": "Example knowledge 286. 知识实例 286"
    },
    {
        "id": 287,
        "text": "Example knowledge 287. 知识实例 287"
    },
    {
        "id": 288,
        "text": "Example knowledge 288. 知识实例 288"
    },
    {
        "id": 289,
        "text": "Example knowledge 289. 知识实例 289"
    },
    {
        "id": 290,
        "text": "Example knowledge 290. 知识实例 290"
    },
    {
        "id": 291,
        "text": "Example knowledge 291. 知识实例 291"
    },
    {
        "id": 292,
        "text": "Example knowledge 292. 知识实例 292"
    },
    {
        "id": 293,
        "text": "Example knowledge 293. 知识实例 293"
    },
    {
        "id": 294,
        "text": "Example knowledge 294. 知识实例 294"
    },
    {
        "id": 295,
        "text": "Example knowledge 295. 知识实例 295"
    },
    {
        "id": 296,
        "text": "Example knowledge 296. 知识实例 296"
    },
    {
        "id": 297,
        "text": "Example knowledge 297. 知识实例 297"
    },
    {
        "id": 298,
        "text": "Example knowledge 298. 知识实例 298"
    },
    {
        "id": 299,
        "text": "Example knowledge 299. 知识实例 299"
    },
    {
        "id": 300,
        "text": "Example knowledge 300. 知识实例 300"
    },
    {
        "id": 301,
        "text": "Example knowledge 301. 知识实例 301"
    },
    {
        "id": 302,
        "text": "Example knowledge 302. 知识实例 302"
    },
    {
        "id": 303,
        "text": "Example knowledge 303. 知识实例 303"
    },
    {
        "id": 304,
        "text": "Example knowledge 304. 知识实例 304"
    },
    {
        "id": 305,
        "text": "Example knowledge 305. 知识实例 305"
    },
    {
        "id": 306,
        "text": "Example knowledge 306. 知识实例 306"
    },
    {
        "id": 307,
        "text": "Example knowledge 307. 知识实例 307"
    },
    {
        "id": 308,
        "text": "Example knowledge 308. 知识实例 308"
    },
    {
        "id": 309,
        "text": "Example knowledge 309. 知识实例 309"
    },
    {
        "id": 310,
        "text": "Example knowledge 310. 知识实例 310"
    },
    {
        "id": 311,
        "text": "Example knowledge 311. 知识实例 311"
    },
    {
        "id": 312,
        "text": "Example knowledge 312. 知识实例 312"
    },
    {
        "id": 313,
        "text": "Example knowledge 313. 知识实例 313"
    },
    {
        "id": 314,
        "text": "Example knowledge 314. 知识实例 314"
    },
    {
        "id": 315,
        "text": "Example knowledge 315. 知识实例 315"
    },
    {
        "id": 316,
        "text": "Example knowledge 316. 知识实例 316"
    },
    {
        "id": 317,
        "text": "Example knowledge 317. 知识实例 317"
    },
    {
        "id": 318,
        "text": "Example knowledge 318. 知识实例 318"
    },
    {
        "id": 319,
        "text": "Example knowledge 319. 知识实例 319"
    },
    {
        "id": 320,
        "text": "Example knowledge 320. 知识实例 320"
    },
    {
        "id": 321,
        "text": "Example knowledge 321. 知识实例 321"
    },
    {
        "id": 322,
        "text": "Example knowledge 322. 知识实例 322"
    },
    {
        "id": 323,
        "text": "Example knowledge 323. 知识实例 323"
    },
    {
        "id": 324,
        "text": "Example knowledge 324. 知识实例 324"
    },
    {
        "id": 325,
        "text": "Example knowledge 325. 知识实例 325"
    },
    {
        "id": 326,
        "text": "Example knowledge 326. 知识实例 326"
    },
    {
        "id": 327,
        "text": "Example knowledge 327. 知识实例 327"
    },
    {
        "id": 328,
        "text": "Example knowledge 328. 知识实例 328"
    },
    {
        "id": 329,
        "text": "Example knowledge 329. 知识实例 329"
    },
    {
        "id": 330,
        "text": "Example knowledge 330. 知识实例 330"
    },
    {
        "id": 331,
        "text": "Example knowledge 331. 知识实例 331"
    },
    {
        "id": 332,
        "text": "Example knowledge 332. 知识实例 332"
    },
    {
        "id": 333,
        "text": "Example knowledge 333. 知识实例 333"
    },
    {
        "id": 334,
        "text": "Example knowledge 334. 知识实例 334"
    },
    {
        "id": 335,
        "text": "Example knowledge 335. 知识实例 335"
    },
    {
        "id": 336,
        "text": "Example knowledge 336. 知识实例 336"
    },
    {
        "id": 337,
        "text": "Example knowledge 337. 知识实例 337"
    },
    {
        "id": 338,
        "text": "Example knowledge 338. 知识实例 338"
    },
    {
        "id": 339,
        "text": "Example knowledge 339. 知识实例 339"
    },
    {
        "id": 340,
        "text": "Example knowledge 340. 知识实例 340"
    },
    {
        "id": 341,
        "text": "Example knowledge 341. 知识实例 341"
    },
    {
        "id": 342,
        "text": "Example knowledge 342. 知识实例 342"
    },
    {
        "id": 343,
        "text": "Example knowledge 343. 知识实例 343"
    },
    {
        "id": 344,
        "text": "Example knowledge 344. 知识实例 344"
    },
    {
        "id": 345,
        "text": "Example knowledge 345. 知识实例 345"
    },
    {
        "id": 346,
        "text": "Example knowledge 346. 知识实例 346"
    },
    {
        "id": 347,
        "text": "Example knowledge 347. 知识实例 347"
    },
    {
        "id": 348,
        "text": "Example knowledge 348. 知识实例 348"
    },
    {
        "id": 349,
        "text": "Example knowledge 349. 知识实例 349"
    },
    {
        "id": 350,
        "text": "Example knowledge 350. 知识实例 350"
    },
    {
        "id": 351,
        "text": "Example knowledge 351. 知识实例 351"
    },
    {
        "id": 352,
        "text": "Example knowledge 352. 知识实例 352"
    },
    {
        "id": 353,
        "text": "Example knowledge 353. 知识实例 353"
    },
    {
        "id": 354,
        "text": "Example knowledge 354. 知识实例 354"
    },
    {
        "id": 355,
        "text": "Example knowledge 355. 知识实例 355"
    },
    {
        "id": 356,
        "text": "Example knowledge 356. 知识实例 356"
    },
    {
        "id": 357,
        "text": "Example knowledge 357. 知识实例 357"
    },
    {
        "id": 358,
        "text": "Example knowledge 358. 知识实例 358"
    },
    {
        "id": 359,
        "text": "Example knowledge 359. 知识实例 359"
    },
    {
        "id": 360,
        "text": "Example knowledge 360. 知识实例 360"
    },
    {
        "id": 361,
        "text": "Example knowledge 361. 知识实例 361"
    },
    {
        "id": 362,
        "text": "Example knowledge 362. 知识实例 362"
    },
    {
        "id": 363,
        "text": "Example knowledge 363. 知识实例 363"
    },
    {
        "id": 364,
        "text": "Example knowledge 364. 知识实例 364"
    },
    {
        "id": 365,
        "text": "Example knowledge 365. 知识实例 365"
    },
    {
        "id": 366,
        "text": "Example knowledge 366. 知识实例 366"
    },
    {
        "id": 367,
        "text": "Example knowledge 367. 知识实例 367"
    },
    {
        "id": 368,
        "text": "Example knowledge 368. 知识实例 368"
    },
    {
        "id": 369,
        "text": "Example knowledge 369. 知识实例 369"
    },
    {
        "id": 370,
        "text": "Example knowledge 370. 知识实例 370"
    },
    {
        "id": 371,
        "text": "Example knowledge 371. 知识实例 371"
    },
    {
        "id": 372,
        "text": "Example knowledge 372. 知识实例 372"
    },
    {
        "id": 373,
        "text": "Example knowledge 373. 知识实例 373"
    },
    {
        "id": 374,
        "text": "Example knowledge 374. 知识实例 374"
    },
    {
        "id": 375,
        "text": "Example knowledge 375. 知识实例 375"
    },
    {
        "id": 376,
        "text": "Example knowledge 376. 知识实例 376"
    },
    {
        "id": 377,
        "text": "Example knowledge 377. 知识实例 377"
    },
    {
        "id": 378,
        "text": "Example knowledge 378. 知识实例 378"
    },
    {
        "id": 379,
        "text": "Example knowledge 379. 知识实例 379"
    },
    {
        "id": 380,
        "text": "Example knowledge 380. 知识实例 380"
    },
    {
        "id": 381,
        "text": "Example knowledge 381. 知识实例 381"
    },
    {
        "id": 382,
        "text": "Example knowledge 382. 知识实例 382"
    },
    {
        "id": 383,
        "text": "Example knowledge 383. 知识实例 383"
    },
    {
        "id": 384,
        "text": "Example knowledge 384. 知识实例 384"
    },
    {
        "id": 385,
        "text": "Example knowledge 385. 知识实例 385"
    },
    {
        "id": 386,
        "text": "Example knowledge 386. 知识实例 386"
    },
    {
        "id": 387,
        "text": "Example knowledge 387. 知识实例 387"
    },
    {
        "id": 388,
        "text": "Example knowledge 388. 知识实例 388"
    },
    {
        "id": 389,
        "text": "Example knowledge 389. 知识实例 389"
    },
    {
        "id": 390,
        "text": "Example knowledge 390. 知识实例 390"
    },
    {
        "id": 391,
        "text": "Example knowledge 391. 知识实例 391"
    },
    {
        "id": 392,
        "text": "Example knowledge 392. 知识实例 392"
    },
    {
        "id": 393,
        "text": "Example knowledge 393. 知识实例 393"
    },
    {
        "id": 394,
        "text": "Example knowledge 394. 知识实例 394"
    },
    {
        "id": 395,
        "text": "Example knowledge 395. 知识实例 395"
    },
    {
        "id": 396,
        "text": "Example knowledge 396. 知识实例 396"
    },
    {
        "id": 397,
        "text": "Example knowledge 397. 知识实例 397"
    },
    {
        "id": 398,
        "text": "Example knowledge 398. 知识实例 398"
    },
    {
        "id": 399,
        "text": "Example knowledge 399. 知识实例 399"
    },
    {
        "id": 400,
        "text": "Example knowledge 400. 知识实例 400"
    },
    {
        "id": 401,
        "text": "Example knowledge 401. 知识实例 401"
    },
    {
        "id": 402,
        "text": "Example knowledge 402. 知识实例 402"
    },
    {
        "id": 403,
        "text": "Example knowledge 403. 知识实例 403"
    },
    {
        "id": 404,
        "text": "Example knowledge 404. 知识实例 404"
    },
    {
        "id": 405,
        "text": "Example knowledge 405. 知识实例 405"
    },
    {
        "id": 406,
        "text": "Example knowledge 406. 知识实例 406"
    },
    {
        "id": 407,
        "text": "Example knowledge 407. 知识实例 407"
    },
    {
        "id": 408,
        "text": "Example knowledge 408. 知识实例 408"
    },
    {
        "id": 409,
        "text": "Example knowledge 409. 知识实例 409"
    },
    {
        "id": 410,
        "text": "Example knowledge 410. 知识实例 410"
    },
    {
        "id": 411,
        "text": "Example knowledge 411. 知识实例 411"
    },
    {
        "id": 412,
        "text": "Example knowledge 412. 知识实例 412"
    },
    {
        "id": 413,
        "text": "Example knowledge 413. 知识实例 413"
    },
    {
        "id": 414,
        "text": "Example knowledge 414. 知识实例 414"
    },
    {
        "id": 415,
        "text": "Example knowledge 415. 知识实例 415"
    },
    {
        "id": 416,
        "text": "Example knowledge 416. 知识实例 416"
    },
    {
        "id": 417,
        "text": "Example knowledge 417. 知识实例 417"
    },
    {
        "id": 418,
        "text": "Example knowledge 418. 知识实例 418"
    },
    {
        "id": 419,
        "text": "Example knowledge 419. 知识实例 419"
    },
    {
        "id": 420,
        "text": "Example knowledge 420. 知识实例 420"
    },
    {
        "id": 421,
        "text": "Example knowledge 421. 知识实例 421"
    },
    {
        "id": 422,
        "text": "Example knowledge 422. 知识实例 422"
    },
    {
        "id": 423,
        "text": "Example knowledge 423. 知识实例 423"
    },
    {
        "id": 424,
        "text": "Example knowledge 424. 知识实例 424"
    },
    {
        "id": 425,
        "text": "Example knowledge 425. 知识实例 425"
    },
    {
        "id": 426,
        "text": "Example knowledge 426. 知识实例 426"
    },
    {
        "id": 427,
        "text": "Example knowledge 427. 知识实例 427"
    },
    {
        "id": 428,
        "text": "Example knowledge 428. 知识实例 428"
    },
    {
        "id": 429,
        "text": "Example knowledge 429. 知识实例 429"
    },
    {
        "id": 430,
        "text": "Example knowledge 430. 知识实例 430"
    },
    {
        "id": 431,
        "text": "Example knowledge 431. 知识实例 431"
    },
    {
        "id": 432,
        "text": "Example knowledge 432. 知识实例 432"
    },
    {
        "id": 433,
        "text": "Example knowledge 433. 知识实例 433"
    },
    {
        "id": 434,
        "text": "Example knowledge 434. 知识实例 434"
    },
    {
        "id": 435,
        "text": "Example knowledge 435. 知识实例 435"
    },
    {
        "id": 436,
        "text": "Example knowledge 436. 知识实例 436"
    },
    {
        "id": 437,
        "text": "Example knowledge 437. 知识实例 437"
    },
    {
        "id": 438,
        "text": "Example knowledge 438. 知识实例 438"
    },
    {
        "id": 439,
        "text": "Example knowledge 439. 知识实例 439"
    },
    {
        "id": 440,
        "text": "Example knowledge 440. 知识实例 440"
    },
    {
        "id": 441,
        "text": "Example knowledge 441. 知识实例 441"
    },
    {
        "id": 442,
        "text": "Example knowledge 442. 知识实例 442"
    },
    {
        "id": 443,
        "text": "Example knowledge 443. 知识实例 443"
    },
    {
        "id": 444,
        "text": "Example knowledge 444. 知识实例 444"
    },
    {
        "id": 445,
        "text": "Example knowledge 445. 知识实例 445"
    },
    {
        "id": 446,
        "text": "Example knowledge 446. 知识实例 446"
    },
    {
        "id": 447,
        "text": "Example knowledge 447. 知识实例 447"
    },
    {
        "id": 448,
        "text": "Example knowledge 448. 知识实例 448"
    },
    {
        "id": 449,
        "text": "Example knowledge 449. 知识实例 449"
    },
    {
        "id": 450,
        "text": "Example knowledge 450. 知识实例 450"
    },
    {
        "id": 451,
        "text": "Example knowledge 451. 知识实例 451"
    },
    {
        "id": 452,
        "text": "Example knowledge 452. 知识实例 452"
    },
    {
        "id": 453,
        "text": "Example knowledge 453. 知识实例 453"
    },
    {
        "id": 454,
        "text": "Example knowledge 454. 知识实例 454"
    },
    {
        "id": 455,
        "text": "Example knowledge 455. 知识实例 455"
    },
    {
        "id": 456,
        "text": "Example knowledge 456. 知识实例 456"
    },
    {
        "id": 457,
        "text": "Example knowledge 457. 知识实例 457"
    },
    {
        "id": 458,
        "text": "Example knowledge 458. 知识实例 458"
    },
    {
        "id": 459,
        "text": "Example knowledge 459. 知识实例 459"
    },
    {
        "id": 460,
        "text": "Example knowledge 460. 知识实例 460"
    },
    {
        "id": 461,
        "text": "Example knowledge 461. 知识实例 461"
    },
    {
        "id": 462,
        "text": "Example knowledge 462. 知识实例 462"
    },
    {
        "id": 463,
        "text": "Example knowledge 463. 知识实例 463"
    },
    {
        "id": 464,
        "text": "Example knowledge 464. 知识实例 464"
    },
    {
        "id": 465,
        "text": "Example knowledge 465. 知识实例 465"
    },
    {
        "id": 466,
        "text": "Example knowledge 466. 知识实例 466"
    },
    {
        "id": 467,
        "text": "Example knowledge 467. 知识实例 467"
    },
    {
        "id": 468,
        "text": "Example knowledge 468. 知识实例 468"
    },
    {
        "id": 469,
        "text": "Example knowledge 469. 知识实例 469"
    },
    {
        "id": 470,
        "text": "Example knowledge 470. 知识实例 470"
    },
    {
        "id": 471,
        "text": "Example knowledge 471. 知识实例 471"
    },
    {
        "id": 472,
        "text": "Example knowledge 472. 知识实例 472"
    },
    {
        "id": 473,
        "text": "Example knowledge 473. 知识实例 473"
    },
    {
        "id": 474,
        "text": "Example knowledge 474. 知识实例 474"
    },
    {
        "id": 475,
        "text": "Example knowledge 475. 知识实例 475"
    },
    {
        "id": 476,
        "text": "Example knowledge 476. 知识实例 476"
    },
    {
        "id": 477,
        "text": "Example knowledge 477. 知识实例 477"
    },
    {
        "id": 478,
        "text": "Example knowledge 478. 知识实例 478"
    },
    {
        "id": 479,
        "text": "Example knowledge 479. 知识实例 479"
    },
    {
        "id": 480,
        "text": "Example knowledge 480. 知识实例 480"
    },
    {
        "id": 481,
        "text": "Example knowledge 481. 知识实例 481"
    },
    {
        "id": 482,
        "text": "Example knowledge 482. 知识实例 482"
    },
    {
        "id": 483,
        "text": "Example knowledge 483. 知识实例 483"
    },
    {
        "id": 484,
        "text": "Example knowledge 484. 知识实例 484"
    },
    {
        "id": 485,
        "text": "Example knowledge 485. 知识实例 485"
    },
    {
        "id": 486,
        "text": "Example knowledge 486. 知识实例 486"
    },
    {
        "id": 487,
        "text": "Example knowledge 487. 知识实例 487"
    },
    {
        "id": 488,
        "text": "Example knowledge 488. 知识实例 488"
    },
    {
        "id": 489,
        "text": "Example knowledge 489. 知识实例 489"
    },
    {
        "id": 490,
        "text": "Example knowledge 490. 知识实例 490"
    },
    {
        "id": 491,
        "text": "Example knowledge 491. 知识实例 491"
    },
    {
        "id": 492,
        "text": "Example knowledge 492. 知识实例 492"
    },
    {
        "id": 493,
        "text": "Example knowledge 493. 知识实例 493"
    },
    {
        "id": 494,
        "text": "Example knowledge 494. 知识实例 494"
    },
    {
        "id": 495,
        "text": "Example knowledge 495. 知识实例 495"
    },
    {
        "id": 496,
        "text": "Example knowledge 496. 知识实例 496"
    },
    {
        "id": 497,
        "text": "Example knowledge 497. 知识实例 497"
    },
    {
        "id": 498,
        "text": "Example knowledge 498. 知识实例 498"
    },
    {
        "id": 499,
        "text": "Example knowledge 499. 知识实例 499"
    }
]