[
    {
        "id": 500,
        "text": "知识实例 500"
    },
    {
        "id": 501,
        "text": "Example knowledge 501."
    },
    {
        "id": 502,
        "text": "知识实例 502"
    },
    {
        "id": 503,
        "text": "Example knowledge 503."
    },
    {
        "id": 504,
        "text": "知识实例 504"
    },
    {
        "id": 505,
        "text": "Example knowledge 505."
    },
    {
        "id": 506,
        "text": "知识实例 506"
    },
    {
        "id": 507,
        "text": "Example knowledge 507."
    },
    {
        "id": 508,
        "text": "知识实例 508"
    },
    {
        "id": 509,
        "text": "Example knowledge 509."
    },
    {
        "id": 510,
        "text": "知识实例 510"
    },
    {
        "id": 511,
        "text": "Example knowledge 511."
    },
    {
        "id": 512,
        "text": "知识实例 512"
    },
    {
        "id": 513,
        "text": "Example knowledge 513."
    },
    {
        "id": 514,
        "text": "知识实例 514"
    },
    {
        "id": 515,
        "text": "Example knowledge 515."
    },
    {
        "id": 516,
        "text": "知识实例 516"
    },
    {
        "id": 517,
        "text": "Example knowledge 517."
    },
    {
        "id": 518,
        "text": "知识实例 518"
    },
    {
        "id": 519,
        "text": "Example knowledge 519."
    },
    {
        "id": 520,
        "text": "知识实例 520"
    },
    {
        "id": 521,
        "text": "Example knowledge 521."
    },
    {
        "id": 522,
        "text": "知识实例 522"
    },
    {
        "id": 523,
        "text": "Example knowledge 523."
    },
    {
        "id": 524,
        "text": "知识实例 524"
    },
    {
        "id": 525,
        "text": "Example knowledge 525."
    },
    {
        "id": 526,
        "text": "知识实例 526"
    },
    {
        "id": 527,
        "text": "Example knowledge 527."
    },
    {
        "id": 528,
        "text": "知识实例 528"
    },
    {
        "id": 529,
        "text": "Example knowledge 529."
    },
    {
        "id": 530,
        "text": "知识实例 530"
    },
    {
        "id": 531,
        "text": "Example knowledge 531."
    },
    {
        "id": 532,
        "text": "知识实例 532"
    },
    {
        "id": 533,
        "text": "Example knowledge 533."
    },
    {
        "id": 534,
        "text": "知识实例 534"
    },
    {
        "id": 535,
        "text": "Example knowledge 535."
    },
    {
        "id": 536,
        "text": "知识实例 536"
    },
    {
        "id": 537,
        "text": "Example knowledge 537."
    },
    {
        "id": 538,
        "text": "知识实例 538"
    },
    {
        "id": 539,
        "text": "Example knowledge 539."
    },
    {
        "id": 540,
        "text": "知识实例 540"
    },
    {
        "id": 541,
        "text": "Example knowledge 541."
    },
    {
        "id": 542,
        "text": "知识实例 542"
    },
    {
        "id": 543,
        "text": "Example knowledge 543."
    },
    {
        "id": 544,
        "text": "知识实例 544"
    },
    {
        "id": 545,
        "text": "Example knowledge 545."
    },
    {
        "id": 546,
        "text": "知识实例 546"
    },
    {
        "id": 547,
        "text": "Example knowledge 547."
    },
    {
        "id": 548,
        "text": "知识实例 548"
    },
    {
        "id": 549,
        "text": "Example knowledge 549."
    },
    {
        "id": 550,
        "text": "知识实例 550"
    },
    {
        "id": 551,
        "text": "Example knowledge 551."
    },
    {
        "id": 552,
        "text": "知识实例 552"
    },
    {
        "id": 553,
        "text": "Example knowledge 553."
    },
    {
        "id": 554,
        "text": "知识实例 554"
    },
    {
        "id": 555,
        "text": "Example knowledge 555."
    },
    {
        "id": 556,
        "text": "知识实例 556"
    },
    {
        "id": 557,
        "text": "Example knowledge 557."
    },
    {
        "id": 558,
        "text": "知识实例 558"
    },
    {
        "id": 559,
        "text": "Example knowledge 559."
    },
    {
        "id": 560,
        "text": "知识实例 560"
    },
    {
        "id": 561,
        "text": "Example knowledge 561."
    },
    {
        "id": 562,
        "text": "知识实例 562"
    },
    {
        "id": 563,
        "text": "Example knowledge 563."
    },
    {
        "id": 564,
        "text": "知识实例 564"
    },
    {
        "id": 565,
        "text": "Example knowledge 565."
    },
    {
        "id": 566,
        "text": "知识实例 566"
    },
    {
        "id": 567,
        "text": "Example knowledge 567."
    },
    {
        "id": 568,
        "text": "知识实例 568"
    },
    {
        "id": 569,
        "text": "Example knowledge 569."
    },
    {
        "id": 570,
        "text": "知识实例 570"
    },
    {
        "id": 571,
        "text": "Example knowledge 571."
    },
    {
        "id": 572,
        "text": "知识实例 572"
    },
    {
        "id": 573,
        "text": "Example knowledge 573."
    },
    {
        "id": 574,
        "text": "知识实例 574"
    },
    {
        "id": 575,
        "text": "Example knowledge 575."
    },
    {
        "id": 576,
        "text": "知识实例 576"
    },
    {
        "id": 577,
        "text": "Example knowledge 577."
    },
    {
        "id": 578,
        "text": "知识实例 578"
    },
    {
        "id": 579,
        "text": "Example knowledge 579."
    },
    {
        "id": 580,
        "text": "知识实例 580"
    },
    {
        "id": 581,
        "text": "Example knowledge 581."
    },
    {
        "id": 582,
        "text": "知识实例 582"
    },
    {
        "id": 583,
        "text": "Example knowledge 583."
    },
    {
        "id": 584,
        "text": "知识实例 584"
    },
    {
        "id": 585,
        "text": "Example knowledge 585."
    },
    {
        "id": 586,
        "text": "知识实例 586"
    },
    {
        "id": 587,
        "text": "Example knowledge 587."
    },
    {
        "id": 588,
        "text": "知识实例 588"
    },
    {
        "id": 589,
        "text": "Example knowledge 589."
    },
    {
        "id": 590,
        "text": "知识实例 590"
    },
    {
        "id": 591,
        "text": "Example knowledge 591."
    },
    {
        "id": 592,
        "text": "知识实例 592"
    },
    {
        "id": 593,
        "text": "Example knowledge 593."
    },
    {
        "id": 594,
        "text": "知识实例 594"
    },
    {
        "id": 595,
        "text": "Example knowledge 595."
    },
    {
        "id": 596,
        "text": "知识实例 596"
    },
    {
        "id": 597,
        "text": "Example knowledge 597."
    },
    {
        "id": 598,
        "text": "知识实例 598"
    },
    {
        "id": 599,
        "text": "Example knowledge 599."
    },
    {
        "id": 600,
        "text": "知识实例 600"
    },
    {
        "id": 601,
        "text": "Example knowledge 601."
    },
    {
        "id": 602,
        "text": "知识实例 602"
    },
    {
        "id": 603,
        "text": "Example knowledge 603."
    },
    {
        "id": 604,
        "text": "知识实例 604"
    },
    {
        "id": 605,
        "text": "Example knowledge 605."
    },
    {
        "id": 606,
        "text": "知识实例 606"
    },
    {
        "id": 607,
        "text": "Example knowledge 607."
    },
    {
        "id": 608,
        "text": "知识实例 608"
    },
    {
        "id": 609,
        "text": "Example knowledge 609."
    },
    {
        "id": 610,
        "text": "知识实例 610"
    },
    {
        "id": 611,
        "text": "Example knowledge 611."
    },
    {
        "id": 612,
        "text": "知识实例 612"
    },
    {
        "id": 613,
        "text": "Example knowledge 613."
    },
    {
        "id": 614,
        "text": "知识实例 614"
    },
    {
        "id": 615,
        "text": "Example knowledge 615."
    },
    {
        "id": 616,
        "text": "知识实例 616"
    },
    {
        "id": 617,
        "text": "Example knowledge 617."
    },
    {
        "id": 618,
        "text": "知识实例 618"
    },
    {
        "id": 619,
        "text": "Example knowledge 619."
    },
    {
        "id": 620,
        "text": "知识实例 620"
    },
    {
        "id": 621,
        "text": "Example knowledge 621."
    },
    {
        "id": 622,
        "text": "知识实例 622"
    },
    {
        "id": 623,
        "text": "Example knowledge 623."
    },
    {
        "id": 624,
        "text": "知识实例 624"
    },
    {
        "id": 625,
        "text": "Example knowledge 625."
    },
    {
        "id": 626,
        "text": "知识实例 626"
    },
    {
        "id": 627,
        "text": "Example knowledge 627."
    },
    {
        "id": 628,
        "text": "知识实例 628"
    },
    {
        "id": 629,
        "text": "Example knowledge 629."
    },
    {
        "id": 630,
        "text": "知识实例 630"
    },
    {
        "id": 631,
        "text": "Example knowledge 631."
    },
    {
        "id": 632,
        "text": "知识实例 632"
    },
    {
        "id": 633,
        "text": "Example knowledge 633."
    },
    {
        "id": 634,
        "text": "知识实例 634"
    },
    {
        "id": 635,
        "text": "Example knowledge 635."
    },
    {
        "id": 636,
        "text": "知识实例 636"
    },
    {
        "id": 637,
        "text": "Example knowledge 637."
    },
    {
        "id": 638,
        "text": "知识实例 638"
    },
    {
        "id": 639,
        "text": "Example knowledge 639."
    },
    {
        "id": 640,
        "text": "知识实例 640"
    },
    {
        "id": 641,
        "text": "Example knowledge 641."
    },
    {
        "id": 642,
        "text": "知识实例 642"
    },
    {
        "id": 643,
        "text": "Example knowledge 643."
    },
    {
        "id": 644,
        "text": "知识实例 644"
    },
    {
        "id": 645,
        "text": "Example knowledge 645."
    },
    {
        "id": 646,
        "text": "知识实例 646"
    },
    {
        "id": 647,
        "text": "Example knowledge 647."
    },
    {
        "id": 648,
        "text": "知识实例 648"
    },
    {
        "id": 649,
        "text": "Example knowledge 649."
    },
    {
        "id": 650,
        "text": "知识实例 650"
    },
    {
        "id": 651,
        "text": "Example knowledge 651."
    },
    {
        "id": 652,
        "text": "知识实例 652"
    },
    {
        "id": 653,
        "text": "Example knowledge 653."
    },
    {
        "id": 654,
        "text": "知识实例 654"
    },
    {
        "id": 655,
        "text": "Example knowledge 655."
    },
    {
        "id": 656,
        "text": "知识实例 656"
    },
    {
        "id": 657,
        "text": "Example knowledge 657."
    },
    {
        "id": 658,
        "text": "知识实例 658"
    },
    {
        "id": 659,
        "text": "Example knowledge 659."
    },
    {
        "id": 660,
        "text": "知识实例 660"
    },
    {
        "id": 661,
        "text": "Example knowledge 661."
    },
    {
        "id": 662,
        "text": "知识实例 662"
    },
    {
        "id": 663,
        "text": "Example knowledge 663."
    },
    {
        "id": 664,
        "text": "知识实例 664"
    },
    {
        "id": 665,
        "text": "Example knowledge 665."
    },
    {
        "id": 666,
        "text": "知识实例 666"
    },
    {
        "id": 667,
        "text": "Example knowledge 667."
    },
    {
        "id": 668,
        "text": "知识实例 668"
    },
    {
        "id": 669,
        "text": "Example knowledge 669."
    },
    {
        "id": 670,
        "text": "知识实例 670"
    },
    {
        "id": 671,
        "text": "Example knowledge 671."
    },
    {
        "id": 672,
        "text": "知识实例 672"
    },
    {
        "id": 673,
        "text": "Example knowledge 673."
    },
    {
        "id": 674,
        "text": "知识实例 674"
    },
    {
        "id": 675,
        "text": "Example knowledge 675."
    },
    {
        "id": 676,
        "text": "知识实例 676"
    },
    {
        "id": 677,
        "text": "Example knowledge 677."
    },
    {
        "id": 678,
        "text": "知识实例 678"
    },
    {
        "id": 679,
        "text": "Example knowledge 679."
    },
    {
        "id": 680,
        "text": "知识实例 680"
    },
    {
        "id": 681,
        "text": "Example knowledge 681."
    },
    {
        "id": 682,
        "text": "知识实例 682"
    },
    {
        "id": 683,
        "text": "Example knowledge 683."
    },
    {
        "id": 684,
        "text": "知识实例 684"
    },
    {
        "id": 685,
        "text": "Example knowledge 685."
    },
    {
        "id": 686,
        "text": "知识实例 686"
    },
    {
        "id": 687,
        "text": "Example knowledge 687."
    },
    {
        "id": 688,
        "text": "知识实例 688"
    },
    {
        "id": 689,
        "text": "Example knowledge 689."
    },
    {
        "id": 690,
        "text": "知识实例 690"
    },
    {
        "id": 691,
        "text": "Example knowledge 691."
    },
    {
        "id": 692,
        "text": "知识实例 692"
    },
    {
        "id": 693,
        "text": "Example knowledge 693."
    },
    {
        "id": 694,
        "text": "知识实例 694"
    },
    {
        "id": 695,
        "text": "Example knowledge 695."
    },
    {
        "id": 696,
        "text": "知识实例 696"
    },
    {
        "id": 697,
        "text": "Example knowledge 697."
    },
    {
        "id": 698,
        "text": "知识实例 698"
    },
    {
        "id": 699,
        "text": "Example knowledge 699."
    },
    {
        "id": 700,
        "text": "知识实例 700"
    },
    {
        "id": 701,
        "text": "Example knowledge 701."
    },
    {
        "id": 702,
        "text": "知识实例 702"
    },
    {
        "id": 703,
        "text": "Example knowledge 703."
    },
    {
        "id": 704,
        "text": "知识实例 704"
    },
    {
        "id": 705,
        "text": "Example knowledge 705."
    },
    {
        "id": 706,
        "text": "知识实例 706"
    },
    {
        "id": 707,
        "text": "Example knowledge 707."
    },
    {
        "id": 708,
        "text": "知识实例 708"
    },
    {
        "id": 709,
        "text": "Example knowledge 709."
    },
    {
        "id": 710,
        "text": "知识实例 710"
    },
    {
        "id": 711,
        "text": "Example knowledge 711."
    },
    {
        "id": 712,
        "text": "知识实例 712"
    },
    {
        "id": 713,
        "text": "Example knowledge 713."
    },
    {
        "id": 714,
        "text": "知识实例 714"
    },
    {
        "id": 715,
        "text": "Example knowledge 715."
    },
    {
        "id": 716,
        "text": "知识实例 716"
    },
    {
        "id": 717,
        "text": "Example knowledge 717."
    },
    {
        "id": 718,
        "text": "知识实例 718"
    },
    {
        "id": 719,
        "text": "Example knowledge 719."
    },
    {
        "id": 720,
        "text": "知识实例 720"
    },
    {
        "id": 721,
        "text": "Example knowledge 721."
    },
    {
        "id": 722,
        "text": "知识实例 722"
    },
    {
        "id": 723,
        "text": "Example knowledge 723."
    },
    {
        "id": 724,
        "text": "知识实例 724"
    },
    {
        "id": 725,
        "text": "Example knowledge 725."
    },
    {
        "id": 726,
        "text": "知识实例 726"
    },
    {
        "id": 727,
        "text": "Example knowledge 727."
    },
    {
        "id": 728,
        "text": "知识实例 728"
    },
    {
        "id": 729,
        "text": "Example knowledge 729."
    },
    {
        "id": 730,
        "text": "知识实例 730"
    },
    {
        "id": 731,
        "text": "Example knowledge 731."
    },
    {
        "id": 732,
        "text": "知识实例 732"
    },
    {
        "id": 733,
        "text": "Example knowledge 733."
    },
    {
        "id": 734,
        "text": "知识实例 734"
    },
    {
        "id": 735,
        "text": "Example knowledge 735."
    },
    {
        "id": 736,
        "text": "知识实例 736"
    },
    {
        "id": 737,
        "text": "Example knowledge 737."
    },
    {
        "id": 738,
        "text": "知识实例 738"
    },
    {
        "id": 739,
        "text": "Example knowledge 739."
    },
    {
        "id": 740,
        "text": "知识实例 740"
    },
    {
        "id": 741,
        "text": "Example knowledge 741."
    },
    {
        "id": 742,
        "text": "知识实例 742"
    },
    {
        "id": 743,
        "text": "Example knowledge 743."
    },
    {
        "id": 744,
        "text": "知识实例 744"
    },
    {
        "id": 745,
        "text": "Example knowledge 745."
    },
    {
        "id": 746,
        "text": "知识实例 746"
    },
    {
        "id": 747,
        "text": "Example knowledge 747."
    },
    {
        "id": 748,
        "text": "知识实例 748"
    },
    {
        "id": 749,
        "text": "Example knowledge 749."
    },
    {
        "id": 750,
        "text": "知识实例 750"
    },
    {
        "id": 751,
        "text": "Example knowledge 751."
    },
    {
        "id": 752,
        "text": "知识实例 752"
    },
    {
        "id": 753,
        "text": "Example knowledge 753."
    },
    {
        "id": 754,
        "text": "知识实例 754"
    },
    {
        "id": 755,
        "text": "Example knowledge 755."
    },
    {
        "id": 756,
        "text": "知识实例 756"
    },
    {
        "id": 757,
        "text": "Example knowledge 757."
    },
    {
        "id": 758,
        "text": "知识实例 758"
    },
    {
        "id": 759,
        "text": "Example knowledge 759."
    },
    {
        "id": 760,
        "text": "知识实例 760"
    },
    {
        "id": 761,
        "text": "Example knowledge 761."
    },
    {
        "id": 762,
        "text": "知识实例 762"
    },
    {
        "id": 763,
        "text": "Example knowledge 763."
    },
    {
        "id": 764,
        "text": "知识实例 764"
    },
    {
        "id": 765,
        "text": "Example knowledge 765."
    },
    {
        "id": 766,
        "text": "知识实例 766"
    },
    {
        "id": 767,
        "text": "Example knowledge 767."
    },
    {
        "id": 768,
        "text": "知识实例 768"
    },
    {
        "id": 769,
        "text": "Example knowledge 769."
    },
    {
        "id": 770,
        "text": "知识实例 770"
    },
    {
        "id": 771,
        "text": "Example knowledge 771."
    },
    {
        "id": 772,
        "text": "知识实例 772"
    },
    {
        "id": 773,
        "text": "Example knowledge 773."
    },
    {
        "id": 774,
        "text": "知识实例 774"
    },
    {
        "id": 775,
        "text": "Example knowledge 775."
    },
    {
        "id": 776,
        "text": "知识实例 776"
    },
    {
        "id": 777,
        "text": "Example knowledge 777."
    },
    {
        "id": 778,
        "text": "知识实例 778"
    },
    {
        "id": 779,
        "text": "Example knowledge 779."
    },
    {
        "id": 780,
        "text": "知识实例 780"
    },
    {
        "id": 781,
        "text": "Example knowledge 781."
    },
    {
        "id": 782,
        "text": "知识实例 782"
    },
    {
        "id": 783,
        "text": "Example knowledge 783."
    },
    {
        "id": 784,
        "text": "知识实例 784"
    },
    {
        "id": 785,
        "text": "Example knowledge 785."
    },
    {
        "id": 786,
        "text": "知识实例 786"
    },
    {
        "id": 787,
        "text": "Example knowledge 787."
    },
    {
        "id": 788,
        "text": "知识实例 788"
    },
    {
        "id": 789,
        "text": "Example knowledge 789."
    },
    {
        "id": 790,
        "text": "知识实例 790"
    },
    {
        "id": 791,
        "text": "Example knowledge 791."
    },
    {
        "id": 792,
        "text": "知识实例 792"
    },
    {
        "id": 793,
        "text": "Example knowledge 793."
    },
    {
        "id": 794,
        "text": "知识实例 794"
    },
    {
        "id": 795,
        "text": "Example knowledge 795."
    },
    {
        "id": 796,
        "text": "知识实例 796"
    },
    {
        "id": 797,
        "text": "Example knowledge 797."
    },
    {
        "id": 798,
        "text": "知识实例 798"
    },
    {
        "id": 799,
        "text": "Example knowledge 799."
    },
    {
        "id": 800,
        "text": "知识实例 800"
    },
    {
        "id": 801,
        "text": "Example knowledge 801."
    },
    {
        "id": 802,
        "text": "知识实例 802"
    },
    {
        "id": 803,
        "text": "Example knowledge 803."
    },
    {
        "id": 804,
        "text": "知识实例 804"
    },
    {
        "id": 805,
        "text": "Example knowledge 805."
    },
    {
        "id": 806,
        "text": "知识实例 806"
    },
    {
        "id": 807,
        "text": "Example knowledge 807."
    },
    {
        "id": 808,
        "text": "知识实例 808"
    },
    {
        "id": 809,
        "text": "Example knowledge 809."
    },
    {
        "id": 810,
        "text": "知识实例 810"
    },
    {
        "id": 811,
        "text": "Example knowledge 811."
    },
    {
        "id": 812,
        "text": "知识实例 812"
    },
    {
        "id": 813,
        "text": "Example knowledge 813."
    },
    {
        "id": 814,
        "text": "知识实例 814"
    },
    {
        "id": 815,
        "text": "Example knowledge 815."
    },
    {
        "id": 816,
        "text": "知识实例 816"
    },
    {
        "id": 817,
        "text": "Example knowledge 817."
    },
    {
        "id": 818,
        "text": "知识实例 818"
    },
    {
        "id": 819,
        "text": "Example knowledge 819."
    },
    {
        "id": 820,
        "text": "知识实例 820"
    },
    {
        "id": 821,
        "text": "Example knowledge 821."
    },
    {
        "id": 822,
        "text": "知识实例 822"
    },
    {
        "id": 823,
        "text": "Example knowledge 823."
    },
    {
        "id": 824,
        "text": "知识实例 824"
    },
    {
        "id": 825,
        "text": "Example knowledge 825."
    },
    {
        "id": 826,
        "text": "知识实例 826"
    },
    {
        "id": 827,
        "text": "Example knowledge 827."
    },
    {
        "id": 828,
        "text": "知识实例 828"
    },
    {
        "id": 829,
        "text": "Example knowledge 829."
    },
    {
        "id": 830,
        "text": "知识实例 830"
    },
    {
        "id": 831,
        "text": "Example knowledge 831."
    },
    {
        "id": 832,
        "text": "知识实例 832"
    },
    {
        "id": 833,
        "text": "Example knowledge 833."
    },
    {
        "id": 834,
        "text": "知识实例 834"
    },
    {
        "id": 835,
        "text": "Example knowledge 835."
    },
    {
        "id": 836,
        "text": "知识实例 836"
    },
    {
        "id": 837,
        "text": "Example knowledge 837."
    },
    {
        "id": 838,
        "text": "知识实例 838"
    },
    {
        "id": 839,
        "text": "Example knowledge 839."
    },
    {
        "id": 840,
        "text": "知识实例 840"
    },
    {
        "id": 841,
        "text": "Example knowledge 841."
    },
    {
        "id": 842,
        "text": "知识实例 842"
    },
    {
        "id": 843,
        "text": "Example knowledge 843."
    },
    {
        "id": 844,
        "text": "知识实例 844"
    },
    {
        "id": 845,
        "text": "Example knowledge 845."
    },
    {
        "id": 846,
        "text": "知识实例 846"
    },
    {
        "id": 847,
        "text": "Example knowledge 847."
    },
    {
        "id": 848,
        "text": "知识实例 848"
    },
    {
        "id": 849,
        "text": "Example knowledge 849."
    },
    {
        "id": 850,
        "text": "知识实例 850"
    },
    {
        "id": 851,
        "text": "Example knowledge 851."
    },
    {
        "id": 852,
        "text": "知识实例 852"
    },
    {
        "id": 853,
        "text": "Example knowledge 853."
    },
    {
        "id": 854,
        "text": "知识实例 854"
    },
    {
        "id": 855,
        "text": "Example knowledge 855."
    },
    {
        "id": 856,
        "text": "知识实例 856"
    },
    {
        "id": 857,
        "text": "Example knowledge 857."
    },
    {
        "id": 858,
        "text": "知识实例 858"
    },
    {
        "id": 859,
        "text": "Example knowledge 859."
    },
    {
        "id": 860,
        "text": "知识实例 860"
    },
    {
        "id": 861,
        "text": "Example knowledge 861."
    },
    {
        "id": 862,
        "text": "知识实例 862"
    },
    {
        "id": 863,
        "text": "Example knowledge 863."
    },
    {
        "id": 864,
        "text": "知识实例 864"
    },
    {
        "id": 865,
        "text": "Example knowledge 865."
    },
    {
        "id": 866,
        "text": "知识实例 866"
    },
    {
        "id": 867,
        "text": "Example knowledge 867."
    },
    {
        "id": 868,
        "text": "知识实例 868"
    },
    {
        "id": 869,
        "text": "Example knowledge 869."
    },
    {
        "id": 870,
        "text": "知识实例 870"
    },
    {
        "id": 871,
        "text": "Example knowledge 871."
    },
    {
        "id": 872,
        "text": "知识实例 872"
    },
    {
        "id": 873,
        "text": "Example knowledge 873."
    },
    {
        "id": 874,
        "text": "知识实例 874"
    },
    {
        "id": 875,
        "text": "Example knowledge 875."
    },
    {
        "id": 876,
        "text": "知识实例 876"
    },
    {
        "id": 877,
        "text": "Example knowledge 877."
    },
    {
        "id": 878,
        "text": "知识实例 878"
    },
    {
        "id": 879,
        "text": "Example knowledge 879."
    },
    {
        "id": 880,
        "text": "知识实例 880"
    },
    {
        "id": 881,
        "text": "Example knowledge 881."
    },
    {
        "id": 882,
        "text": "知识实例 882"
    },
    {
        "id": 883,
        "text": "Example knowledge 883."
    },
    {
        "id": 884,
        "text": "知识实例 884"
    },
    {
        "id": 885,
        "text": "Example knowledge 885."
    },
    {
        "id": 886,
        "text": "知识实例 886"
    },
    {
        "id": 887,
        "text": "Example knowledge 887."
    },
    {
        "id": 888,
        "text": "知识实例 888"
    },
    {
        "id": 889,
        "text": "Example knowledge 889."
    },
    {
        "id": 890,
        "text": "知识实例 890"
    },
    {
        "id": 891,
        "text": "Example knowledge 891."
    },
    {
        "id": 892,
        "text": "知识实例 892"
    },
    {
        "id": 893,
        "text": "Example knowledge 893."
    },
    {
        "id": 894,
        "text": "知识实例 894"
    },
    {
        "id": 895,
        "text": "Example knowledge 895."
    },
    {
        "id": 896,
        "text": "知识实例 896"
    },
    {
        "id": 897,
        "text": "Example knowledge 897."
    },
    {
        "id": 898,
        "text": "知识实例 898"
    },
    {
        "id": 899,
        "text": "Example knowledge 899."
    },
    {
        "id": 900,
        "text": "知识实例 900"
    },
    {
        "id": 901,
        "text": "Example knowledge 901."
    },
    {
        "id": 902,
        "text": "知识实例 902"
    },
    {
        "id": 903,
        "text": "Example knowledge 903."
    },
    {
        "id": 904,
        "text": "知识实例 904"
    },
    {
        "id": 905,
        "text": "Example knowledge 905."
    },
    {
        "id": 906,
        "text": "知识实例 906"
    },
    {
        "id": 907,
        "text": "Example knowledge 907."
    },
    {
        "id": 908,
        "text": "知识实例 908"
    },
    {
        "id": 909,
        "text": "Example knowledge 909."
    },
    {
        "id": 910,
        "text": "知识实例 910"
    },
    {
        "id": 911,
        "text": "Example knowledge 911."
    },
    {
        "id": 912,
        "text": "知识实例 912"
    },
    {
        "id": 913,
        "text": "Example knowledge 913."
    },
    {
        "id": 914,
        "text": "知识实例 914"
    },
    {
        "id": 915,
        "text": "Example knowledge 915."
    },
    {
        "id": 916,
        "text": "知识实例 916"
    },
    {
        "id": 917,
        "text": "Example knowledge 917."
    },
    {
        "id": 918,
        "text": "知识实例 918"
    },
    {
        "id": 919,
        "text": "Example knowledge 919."
    },
    {
        "id": 920,
        "text": "知识实例 920"
    },
    {
        "id": 921,
        "text": "Example knowledge 921."
    },
    {
        "id": 922,
        "text": "知识实例 922"
    },
    {
        "id": 923,
        "text": "Example knowledge 923."
    },
    {
        "id": 924,
        "text": "知识实例 924"
    },
    {
        "id": 925,
        "text": "Example knowledge 925."
    },
    {
        "id": 926,
        "text": "知识实例 926"
    },
    {
        "id": 927,
        "text": "Example knowledge 927."
    },
    {
        "id": 928,
        "text": "知识实例 928"
    },
    {
        "id": 929,
        "text": "Example knowledge 929."
    },
    {
        "id": 930,
        "text": "知识实例 930"
    },
    {
        "id": 931,
        "text": "Example knowledge 931."
    },
    {
        "id": 932,
        "text": "知识实例 932"
    },
    {
        "id": 933,
        "text": "Example knowledge 933."
    },
    {
        "id": 934,
        "text": "知识实例 934"
    },
    {
        "id": 935,
        "text": "Example knowledge 935."
    },
    {
        "id": 936,
        "text": "知识实例 936"
    },
    {
        "id": 937,
        "text": "Example knowledge 937."
    },
    {
        "id": 938,
        "text": "知识实例 938"
    },
    {
        "id": 939,
        "text": "Example knowledge 939."
    },
    {
        "id": 940,
        "text": "知识实例 940"
    },
    {
        "id": 941,
        "text": "Example knowledge 941."
    },
    {
        "id": 942,
        "text": "知识实例 942"
    },
    {
        "id": 943,
        "text": "Example knowledge 943."
    },
    {
        "id": 944,
        "text": "知识实例 944"
    },
    {
        "id": 945,
        "text": "Example knowledge 945."
    },
    {
        "id": 946,
        "text": "知识实例 946"
    },
    {
        "id": 947,
        "text": "Example knowledge 947."
    },
    {
        "id": 948,
        "text": "知识实例 948"
    },
    {
        "id": 949,
        "text": "Example knowledge 949."
    },
    {
        "id": 950,
        "text": "知识实例 950"
    },
    {
        "id": 951,
        "text": "Example knowledge 951."
    },
    {
        "id": 952,
        "text": "知识实例 952"
    },
    {
        "id": 953,
        "text": "Example knowledge 953."
    },
    {
        "id": 954,
        "text": "知识实例 954"
    },
    {
        "id": 955,
        "text": "Example knowledge 955."
    },
    {
        "id": 956,
        "text": "知识实例 956"
    },
    {
        "id": 957,
        "text": "Example knowledge 957."
    },
    {
        "id": 958,
        "text": "知识实例 958"
    },
    {
        "id": 959,
        "text": "Example knowledge 959."
    },
    {
        "id": 960,
        "text": "知识实例 960"
    },
    {
        "id": 961,
        "text": "Example knowledge 961."
    },
    {
        "id": 962,
        "text": "知识实例 962"
    },
    {
        "id": 963,
        "text": "Example knowledge 963."
    },
    {
        "id": 964,
        "text": "知识实例 964"
    },
    {
        "id": 965,
        "text": "Example knowledge 965."
    },
    {
        "id": 966,
        "text": "知识实例 966"
    },
    {
        "id": 967,
        "text": "Example knowledge 967."
    },
    {
        "id": 968,
        "text": "知识实例 968"
    },
    {
        "id": 969,
        "text": "Example knowledge 969."
    },
    {
        "id": 970,
        "text": "知识实例 970"
    },
    {
        "id": 971,
        "text": "Example knowledge 971."
    },
    {
        "id": 972,
        "text": "知识实例 972"
    },
    {
        "id": 973,
        "text": "Example knowledge 973."
    },
    {
        "id": 974,
        "text": "知识实例 974"
    },
    {
        "id": 975,
        "text": "Example knowledge 975."
    },
    {
        "id": 976,
        "text": "知识实例 976"
    },
    {
        "id": 977,
        "text": "Example knowledge 977."
    },
    {
        "id": 978,
        "text": "知识实例 978"
    },
    {
        "id": 979,
        "text": "Example knowledge 979."
    },
    {
        "id": 980,
        "text": "知识实例 980"
    },
    {
        "id": 981,
        "text": "Example knowledge 981."
    },
    {
        "id": 982,
        "text": "知识实例 982"
    },
    {
        "id": 983,
        "text": "Example knowledge 983."
    },
    {
        "id": 984,
        "text": "知识实例 984"
    },
    {
        "id": 985,
        "text": "Example knowledge 985."
    },
    {
        "id": 986,
        "text": "知识实例 986"
    },
    {
        "id": 987,
        "text": "Example knowledge 987."
    },
    {
        "id": 988,
        "text": "知识实例 988"
    },
    {
        "id": 989,
        "text": "Example knowledge 989."
    },
    {
        "id": 990,
        "text": "知识实例 990"
    },
    {
        "id": 991,
        "text": "Example knowledge 991."
    },
    {
        "id": 992,
        "text": "知识实例 992"
    },
    {
        "id": 993,
        "text": "Example knowledge 993."
    },
    {
        "id": 994,
        "text": "知识实例 994"
    },
    {
        "id": 995,
        "text": "Example knowledge 995."
    },
    {
        "id": 996,
        "text": "知识实例 996"
    },
    {
        "id": 997,
        "text": "Example knowledge 997."
    },
    {
        "id": 998,
        "text": "知识实例 998"
    },
    {
        "id": 999,
        "text": "Example knowledge 999."
    }
]